ose_plugin_hbcp/__init__.py
ose_plugin_hbcp/py.typed
ose_plugin_hbcp/search_api/APIClient.py
ose_plugin_hbcp/search_api/APIService.py
ose_plugin_hbcp/search_api/HttpError.py
ose_plugin_hbcp/search_api/__init__.py
ose_plugin_hbcp-0.2.5.dist-info/METADATA
ose_plugin_hbcp-0.2.5.dist-info/WHEEL
ose_plugin_hbcp-0.2.5.dist-info/top_level.txt
ose_plugin_hbcp-0.2.5.dist-info/RECORD
