Metadata-Version: 2.4
Name: ose-plugin-hbcp
Version: 0.2.5
Summary: OntoSpreadEd plugin for HBCP common services
Requires-Python: >=3.12
Requires-Dist: ose-core==0.2.5
